otakugifs/__init__.py
otakugifs/client.py
otakugifs-1.0.4.dist-info/licenses/LICENSE
otakugifs-1.0.4.dist-info/METADATA
otakugifs-1.0.4.dist-info/WHEEL
otakugifs-1.0.4.dist-info/top_level.txt
otakugifs-1.0.4.dist-info/RECORD
