Metadata-Version: 2.4
Name: OTAKUGIFS
Version: 1.0.4
Summary: A Python wrapper for the OtakuGIFS API
Home-page: https://github.com/infinite31/OTAKUGIFS
Author: INFINITE_.
Author-email: work4infinite@gmail.com
Keywords: python,gif-generator,anime,api,wrapper
Classifier: Development Status :: 1 - Planning
Classifier: Intended Audience :: Developers
Classifier: Operating System :: Microsoft :: Windows :: Windows 11
Classifier: License :: OSI Approved :: MIT License
Classifier: Programming Language :: Python :: 3
Requires-Python: >=3.6
License-File: LICENSE
Requires-Dist: httpx
Dynamic: author
Dynamic: author-email
Dynamic: classifier
Dynamic: description
Dynamic: description-content-type
Dynamic: home-page
Dynamic: keywords
Dynamic: license-file
Dynamic: requires-dist
Dynamic: requires-python
Dynamic: summary
